[
  {
    "path": "data/duke.txt",
    "fileType": "txt",
    "lines": [
      {
        "lineNumber": 1,
        "author": {
          "gitId": "itskesin"
        },
        "content": "T | 0 | hello"
      },
      {
        "lineNumber": 2,
        "author": {
          "gitId": "itskesin"
        },
        "content": "T | 0 | sleep"
      },
      {
        "lineNumber": 3,
        "author": {
          "gitId": "itskesin"
        },
        "content": "T | 0 | eat"
      },
      {
        "lineNumber": 4,
        "author": {
          "gitId": "itskesin"
        },
        "content": "E | 0 | repeat | everyday"
      },
      {
        "lineNumber": 5,
        "author": {
          "gitId": "itskesin"
        },
        "content": "D | 0 | sleep | now"
      }
    ],
    "authorContributionMap": {
      "itskesin": 5
    }
  },
  {
    "path": "src/main/java/duke/Duke.java",
    "fileType": "java",
    "lines": [
      {
        "lineNumber": 1,
        "author": {
          "gitId": "itskesin"
        },
        "content": "package duke;"
      },
      {
        "lineNumber": 2,
        "author": {
          "gitId": "itskesin"
        },
        "content": ""
      },
      {
        "lineNumber": 3,
        "author": {
          "gitId": "itskesin"
        },
        "content": "import duke.task.Deadline;"
      },
      {
        "lineNumber": 4,
        "author": {
          "gitId": "itskesin"
        },
        "content": "import duke.task.Event;"
      },
      {
        "lineNumber": 5,
        "author": {
          "gitId": "itskesin"
        },
        "content": "import duke.task.Task;"
      },
      {
        "lineNumber": 6,
        "author": {
          "gitId": "itskesin"
        },
        "content": "import duke.task.ToDo;"
      },
      {
        "lineNumber": 7,
        "author": {
          "gitId": "itskesin"
        },
        "content": ""
      },
      {
        "lineNumber": 8,
        "author": {
          "gitId": "itskesin"
        },
        "content": "import java.io.File;"
      },
      {
        "lineNumber": 9,
        "author": {
          "gitId": "itskesin"
        },
        "content": "import java.io.FileNotFoundException;"
      },
      {
        "lineNumber": 10,
        "author": {
          "gitId": "itskesin"
        },
        "content": "import java.io.FileWriter;"
      },
      {
        "lineNumber": 11,
        "author": {
          "gitId": "itskesin"
        },
        "content": "import java.io.IOException;"
      },
      {
        "lineNumber": 12,
        "author": {
          "gitId": "itskesin"
        },
        "content": "import java.util.Scanner;"
      },
      {
        "lineNumber": 13,
        "author": {
          "gitId": "itskesin"
        },
        "content": "import java.util.ArrayList;"
      },
      {
        "lineNumber": 14,
        "author": {
          "gitId": "itskesin"
        },
        "content": ""
      },
      {
        "lineNumber": 15,
        "author": {
          "gitId": "-"
        },
        "content": "public class Duke {"
      },
      {
        "lineNumber": 16,
        "author": {
          "gitId": "itskesin"
        },
        "content": ""
      },
      {
        "lineNumber": 17,
        "author": {
          "gitId": "itskesin"
        },
        "content": "    private static final String HAPPY_FACE \u003d \"(＾▽＾)\";"
      },
      {
        "lineNumber": 18,
        "author": {
          "gitId": "itskesin"
        },
        "content": "    private static final String SAD_FACE \u003d \"(╥_╥)\";"
      },
      {
        "lineNumber": 19,
        "author": {
          "gitId": "itskesin"
        },
        "content": "    private static final String DIVIDER \u003d \"\u003d\u003d\u003d\u003d\u003d\u003d\u003d\u003d\u003d\u003d\u003d\u003d\u003d\u003d\u003d\u003d\u003d\u003d\u003d\u003d\u003d\u003d\u003d\u003d\u003d\u003d\u003d\u003d\u003d\u003d\u003d\u003d\u003d\u003d\u003d\u003d\u003d\u003d\u003d\u003d\u003d\u003d\u003d\u003d\u003d\u003d\u003d\u003d\u003d\u003d\u003d\";"
      },
      {
        "lineNumber": 20,
        "author": {
          "gitId": "itskesin"
        },
        "content": ""
      },
      {
        "lineNumber": 21,
        "author": {
          "gitId": "-"
        },
        "content": "    public static void main(String[] args) {"
      },
      {
        "lineNumber": 22,
        "author": {
          "gitId": "itskesin"
        },
        "content": "        printWelcomeMessage();"
      },
      {
        "lineNumber": 23,
        "author": {
          "gitId": "itskesin"
        },
        "content": "        Scanner sc \u003d new Scanner(System.in);"
      },
      {
        "lineNumber": 24,
        "author": {
          "gitId": "itskesin"
        },
        "content": "        String name \u003d sc.nextLine();"
      },
      {
        "lineNumber": 25,
        "author": {
          "gitId": "itskesin"
        },
        "content": "        printUserGreeting(name);"
      },
      {
        "lineNumber": 26,
        "author": {
          "gitId": "itskesin"
        },
        "content": "        ArrayList\u003cTask\u003e tasks \u003d new ArrayList\u003cTask\u003e();"
      },
      {
        "lineNumber": 27,
        "author": {
          "gitId": "itskesin"
        },
        "content": "        try {"
      },
      {
        "lineNumber": 28,
        "author": {
          "gitId": "itskesin"
        },
        "content": "            retrieve(tasks);"
      },
      {
        "lineNumber": 29,
        "author": {
          "gitId": "itskesin"
        },
        "content": "        } catch (FileNotFoundException e) {"
      },
      {
        "lineNumber": 30,
        "author": {
          "gitId": "itskesin"
        },
        "content": "            e.printStackTrace();"
      },
      {
        "lineNumber": 31,
        "author": {
          "gitId": "itskesin"
        },
        "content": "        }"
      },
      {
        "lineNumber": 32,
        "author": {
          "gitId": "itskesin"
        },
        "content": "        manageTasks(sc, name, tasks);"
      },
      {
        "lineNumber": 33,
        "author": {
          "gitId": "itskesin"
        },
        "content": "    }"
      },
      {
        "lineNumber": 34,
        "author": {
          "gitId": "itskesin"
        },
        "content": ""
      },
      {
        "lineNumber": 35,
        "author": {
          "gitId": "itskesin"
        },
        "content": "    private static ArrayList\u003cTask\u003e retrieve(ArrayList\u003cTask\u003e tasks) throws FileNotFoundException {"
      },
      {
        "lineNumber": 36,
        "author": {
          "gitId": "itskesin"
        },
        "content": "        File f \u003d new File(\"C:\\\\repos\\\\IP\\\\data\\\\duke.txt\"); // create a File for the given file path"
      },
      {
        "lineNumber": 37,
        "author": {
          "gitId": "itskesin"
        },
        "content": "        Scanner s \u003d new Scanner(f); // create a Scanner using the File as the source"
      },
      {
        "lineNumber": 38,
        "author": {
          "gitId": "itskesin"
        },
        "content": "        while (s.hasNext()) {"
      },
      {
        "lineNumber": 39,
        "author": {
          "gitId": "itskesin"
        },
        "content": "            String input \u003d s.nextLine();"
      },
      {
        "lineNumber": 40,
        "author": {
          "gitId": "itskesin"
        },
        "content": "            String[] parseInput \u003d input.split(\"[|]\");"
      },
      {
        "lineNumber": 41,
        "author": {
          "gitId": "itskesin"
        },
        "content": "            switch (parseInput[0].trim()) {"
      },
      {
        "lineNumber": 42,
        "author": {
          "gitId": "itskesin"
        },
        "content": "                case (\"T\"):"
      },
      {
        "lineNumber": 43,
        "author": {
          "gitId": "itskesin"
        },
        "content": "                    tasks.add(new ToDo(parseInput[2].trim()));"
      },
      {
        "lineNumber": 44,
        "author": {
          "gitId": "itskesin"
        },
        "content": "                    break;"
      },
      {
        "lineNumber": 45,
        "author": {
          "gitId": "itskesin"
        },
        "content": "                case (\"E\"):"
      },
      {
        "lineNumber": 46,
        "author": {
          "gitId": "itskesin"
        },
        "content": "                    tasks.add(new Event(parseInput[2].trim(), parseInput[3].trim()));"
      },
      {
        "lineNumber": 47,
        "author": {
          "gitId": "itskesin"
        },
        "content": "                    break;"
      },
      {
        "lineNumber": 48,
        "author": {
          "gitId": "itskesin"
        },
        "content": "                case (\"D\"):"
      },
      {
        "lineNumber": 49,
        "author": {
          "gitId": "itskesin"
        },
        "content": "                    tasks.add(new Deadline(parseInput[2].trim(), parseInput[3].trim()));"
      },
      {
        "lineNumber": 50,
        "author": {
          "gitId": "itskesin"
        },
        "content": "                    break;"
      },
      {
        "lineNumber": 51,
        "author": {
          "gitId": "itskesin"
        },
        "content": "            }"
      },
      {
        "lineNumber": 52,
        "author": {
          "gitId": "itskesin"
        },
        "content": "            if (parseInput[1].trim().equals(\"1\")) {"
      },
      {
        "lineNumber": 53,
        "author": {
          "gitId": "itskesin"
        },
        "content": "                tasks.get(tasks.size()-1).updateTask();"
      },
      {
        "lineNumber": 54,
        "author": {
          "gitId": "itskesin"
        },
        "content": "            }"
      },
      {
        "lineNumber": 55,
        "author": {
          "gitId": "itskesin"
        },
        "content": "        }"
      },
      {
        "lineNumber": 56,
        "author": {
          "gitId": "itskesin"
        },
        "content": "        return tasks;"
      },
      {
        "lineNumber": 57,
        "author": {
          "gitId": "itskesin"
        },
        "content": "    }"
      },
      {
        "lineNumber": 58,
        "author": {
          "gitId": "itskesin"
        },
        "content": ""
      },
      {
        "lineNumber": 59,
        "author": {
          "gitId": "itskesin"
        },
        "content": "    private static void manageTasks(Scanner sc, String name, ArrayList\u003cTask\u003e tasks) {"
      },
      {
        "lineNumber": 60,
        "author": {
          "gitId": "itskesin"
        },
        "content": ""
      },
      {
        "lineNumber": 61,
        "author": {
          "gitId": "itskesin"
        },
        "content": "        while (true) {"
      },
      {
        "lineNumber": 62,
        "author": {
          "gitId": "itskesin"
        },
        "content": "            String input \u003d sc.nextLine();"
      },
      {
        "lineNumber": 63,
        "author": {
          "gitId": "itskesin"
        },
        "content": "            String[] parseInput \u003d input.split(\" \", 2);"
      },
      {
        "lineNumber": 64,
        "author": {
          "gitId": "itskesin"
        },
        "content": "            String command \u003d parseInput[0];"
      },
      {
        "lineNumber": 65,
        "author": {
          "gitId": "itskesin"
        },
        "content": "            //parseInput[1].isEmpty() for empty string, not empty spaces"
      },
      {
        "lineNumber": 66,
        "author": {
          "gitId": "itskesin"
        },
        "content": ""
      },
      {
        "lineNumber": 67,
        "author": {
          "gitId": "itskesin"
        },
        "content": "            try {"
      },
      {
        "lineNumber": 68,
        "author": {
          "gitId": "itskesin"
        },
        "content": "                if (command.equalsIgnoreCase(\"done\")) {"
      },
      {
        "lineNumber": 69,
        "author": {
          "gitId": "itskesin"
        },
        "content": "                    try {"
      },
      {
        "lineNumber": 70,
        "author": {
          "gitId": "itskesin"
        },
        "content": "                        printDoneTasks(tasks, parseInput[1]);"
      },
      {
        "lineNumber": 71,
        "author": {
          "gitId": "itskesin"
        },
        "content": "                    } catch (ArrayIndexOutOfBoundsException e) {"
      },
      {
        "lineNumber": 72,
        "author": {
          "gitId": "itskesin"
        },
        "content": "                        System.out.println(String.format(\"%50s\", \"Please include task number \" + SAD_FACE));"
      },
      {
        "lineNumber": 73,
        "author": {
          "gitId": "itskesin"
        },
        "content": "                        System.out.println(DIVIDER);"
      },
      {
        "lineNumber": 74,
        "author": {
          "gitId": "itskesin"
        },
        "content": "                    }"
      },
      {
        "lineNumber": 75,
        "author": {
          "gitId": "itskesin"
        },
        "content": "                } else if (command.equalsIgnoreCase(\"list\")) {"
      },
      {
        "lineNumber": 76,
        "author": {
          "gitId": "itskesin"
        },
        "content": "                    printList(tasks);"
      },
      {
        "lineNumber": 77,
        "author": {
          "gitId": "itskesin"
        },
        "content": "                } else if (command.equalsIgnoreCase(\"todo\")) {"
      },
      {
        "lineNumber": 78,
        "author": {
          "gitId": "itskesin"
        },
        "content": "                    addToDo(tasks, parseInput);"
      },
      {
        "lineNumber": 79,
        "author": {
          "gitId": "itskesin"
        },
        "content": "                } else if (command.equalsIgnoreCase(\"bye\")) {"
      },
      {
        "lineNumber": 80,
        "author": {
          "gitId": "itskesin"
        },
        "content": "                    try {"
      },
      {
        "lineNumber": 81,
        "author": {
          "gitId": "itskesin"
        },
        "content": "                        save(tasks);"
      },
      {
        "lineNumber": 82,
        "author": {
          "gitId": "itskesin"
        },
        "content": "                    } catch (IOException e) {"
      },
      {
        "lineNumber": 83,
        "author": {
          "gitId": "itskesin"
        },
        "content": "                        e.printStackTrace();"
      },
      {
        "lineNumber": 84,
        "author": {
          "gitId": "itskesin"
        },
        "content": "                    }"
      },
      {
        "lineNumber": 85,
        "author": {
          "gitId": "itskesin"
        },
        "content": "                    printByeMessage(name);"
      },
      {
        "lineNumber": 86,
        "author": {
          "gitId": "itskesin"
        },
        "content": "                    break;"
      },
      {
        "lineNumber": 87,
        "author": {
          "gitId": "itskesin"
        },
        "content": "                } else if (command.equalsIgnoreCase(\"event\")) {"
      },
      {
        "lineNumber": 88,
        "author": {
          "gitId": "itskesin"
        },
        "content": "                    try {"
      },
      {
        "lineNumber": 89,
        "author": {
          "gitId": "itskesin"
        },
        "content": "                        addEvent(tasks, parseInput[1]);"
      },
      {
        "lineNumber": 90,
        "author": {
          "gitId": "itskesin"
        },
        "content": "                    } catch (ArrayIndexOutOfBoundsException e) {"
      },
      {
        "lineNumber": 91,
        "author": {
          "gitId": "itskesin"
        },
        "content": "                        System.out.println(String.format(\"%50s\", \"Oops! Information is incomplete \" + SAD_FACE));"
      },
      {
        "lineNumber": 92,
        "author": {
          "gitId": "itskesin"
        },
        "content": "                        System.out.println(DIVIDER);"
      },
      {
        "lineNumber": 93,
        "author": {
          "gitId": "itskesin"
        },
        "content": "                    }"
      },
      {
        "lineNumber": 94,
        "author": {
          "gitId": "itskesin"
        },
        "content": "                } else if (command.equalsIgnoreCase(\"deadline\")) {"
      },
      {
        "lineNumber": 95,
        "author": {
          "gitId": "itskesin"
        },
        "content": "                    try {"
      },
      {
        "lineNumber": 96,
        "author": {
          "gitId": "itskesin"
        },
        "content": "                        addDeadline(tasks, parseInput[1]);"
      },
      {
        "lineNumber": 97,
        "author": {
          "gitId": "itskesin"
        },
        "content": "                    } catch (ArrayIndexOutOfBoundsException e) {"
      },
      {
        "lineNumber": 98,
        "author": {
          "gitId": "itskesin"
        },
        "content": "                        System.out.println(String.format(\"%50s\", \"Oops! Information is incomplete \" + SAD_FACE));"
      },
      {
        "lineNumber": 99,
        "author": {
          "gitId": "itskesin"
        },
        "content": "                        System.out.println(DIVIDER);"
      },
      {
        "lineNumber": 100,
        "author": {
          "gitId": "itskesin"
        },
        "content": "                    }"
      },
      {
        "lineNumber": 101,
        "author": {
          "gitId": "itskesin"
        },
        "content": "                } else if (command.equalsIgnoreCase(\"delete\")) {"
      },
      {
        "lineNumber": 102,
        "author": {
          "gitId": "itskesin"
        },
        "content": "                    try {"
      },
      {
        "lineNumber": 103,
        "author": {
          "gitId": "itskesin"
        },
        "content": "                        deleteTask(tasks, parseInput[1]);"
      },
      {
        "lineNumber": 104,
        "author": {
          "gitId": "itskesin"
        },
        "content": "                    } catch (IndexOutOfBoundsException e) {"
      },
      {
        "lineNumber": 105,
        "author": {
          "gitId": "itskesin"
        },
        "content": "                        System.out.println(String.format(\"%50s\", \"Please include task number in the list \" + SAD_FACE));"
      },
      {
        "lineNumber": 106,
        "author": {
          "gitId": "itskesin"
        },
        "content": "                        System.out.println(DIVIDER);"
      },
      {
        "lineNumber": 107,
        "author": {
          "gitId": "itskesin"
        },
        "content": "                    } catch (NumberFormatException e) {"
      },
      {
        "lineNumber": 108,
        "author": {
          "gitId": "itskesin"
        },
        "content": "                        System.out.println(String.format(\"%50s\", \"Oops! Information is incomplete \" + SAD_FACE));"
      },
      {
        "lineNumber": 109,
        "author": {
          "gitId": "itskesin"
        },
        "content": "                        System.out.println(DIVIDER);"
      },
      {
        "lineNumber": 110,
        "author": {
          "gitId": "itskesin"
        },
        "content": "                    }"
      },
      {
        "lineNumber": 111,
        "author": {
          "gitId": "itskesin"
        },
        "content": "                } else {"
      },
      {
        "lineNumber": 112,
        "author": {
          "gitId": "itskesin"
        },
        "content": "                    throw new DukeException();"
      },
      {
        "lineNumber": 113,
        "author": {
          "gitId": "itskesin"
        },
        "content": "                }"
      },
      {
        "lineNumber": 114,
        "author": {
          "gitId": "itskesin"
        },
        "content": "            } catch (DukeException e) {"
      },
      {
        "lineNumber": 115,
        "author": {
          "gitId": "itskesin"
        },
        "content": "                //catch invalid commands"
      },
      {
        "lineNumber": 116,
        "author": {
          "gitId": "itskesin"
        },
        "content": "                System.out.println(String.format(\"%50s\", \"Oops! I don\u0027t know what that means \" + SAD_FACE));"
      },
      {
        "lineNumber": 117,
        "author": {
          "gitId": "itskesin"
        },
        "content": "                System.out.println(DIVIDER);"
      },
      {
        "lineNumber": 118,
        "author": {
          "gitId": "itskesin"
        },
        "content": "            }"
      },
      {
        "lineNumber": 119,
        "author": {
          "gitId": "itskesin"
        },
        "content": "        }"
      },
      {
        "lineNumber": 120,
        "author": {
          "gitId": "itskesin"
        },
        "content": "    }"
      },
      {
        "lineNumber": 121,
        "author": {
          "gitId": "itskesin"
        },
        "content": ""
      },
      {
        "lineNumber": 122,
        "author": {
          "gitId": "itskesin"
        },
        "content": "    private static void deleteTask(ArrayList\u003cTask\u003e tasks, String s) {"
      },
      {
        "lineNumber": 123,
        "author": {
          "gitId": "itskesin"
        },
        "content": "        int removeTask \u003d Integer.parseInt(s)-1;"
      },
      {
        "lineNumber": 124,
        "author": {
          "gitId": "itskesin"
        },
        "content": "        String taskInformation \u003d String.valueOf(tasks.get(removeTask));"
      },
      {
        "lineNumber": 125,
        "author": {
          "gitId": "itskesin"
        },
        "content": "        System.out.println(String.format(\"%50s\", \"Noted. I\u0027ve removed this task: \"+ HAPPY_FACE));"
      },
      {
        "lineNumber": 126,
        "author": {
          "gitId": "itskesin"
        },
        "content": "        System.out.println(String.format(\"%50s\", taskInformation));"
      },
      {
        "lineNumber": 127,
        "author": {
          "gitId": "itskesin"
        },
        "content": "        tasks.remove(removeTask);"
      },
      {
        "lineNumber": 128,
        "author": {
          "gitId": "itskesin"
        },
        "content": "        System.out.println(String.format(\"%50s\", \"Now you have \" + tasks.size() + \" tasks in the list.\"));"
      },
      {
        "lineNumber": 129,
        "author": {
          "gitId": "itskesin"
        },
        "content": "        System.out.println(DIVIDER);"
      },
      {
        "lineNumber": 130,
        "author": {
          "gitId": "itskesin"
        },
        "content": "    }"
      },
      {
        "lineNumber": 131,
        "author": {
          "gitId": "itskesin"
        },
        "content": ""
      },
      {
        "lineNumber": 132,
        "author": {
          "gitId": "itskesin"
        },
        "content": "    private static void save(ArrayList\u003cTask\u003e tasks) throws IOException {"
      },
      {
        "lineNumber": 133,
        "author": {
          "gitId": "itskesin"
        },
        "content": "        FileWriter fw \u003d new FileWriter(\"C:\\\\repos\\\\IP\\\\data\\\\duke.txt\",false);"
      },
      {
        "lineNumber": 134,
        "author": {
          "gitId": "itskesin"
        },
        "content": "        for (Task i : tasks) {"
      },
      {
        "lineNumber": 135,
        "author": {
          "gitId": "itskesin"
        },
        "content": "            fw.write(i.saveTask());"
      },
      {
        "lineNumber": 136,
        "author": {
          "gitId": "itskesin"
        },
        "content": "            fw.write(System.lineSeparator());"
      },
      {
        "lineNumber": 137,
        "author": {
          "gitId": "itskesin"
        },
        "content": "        }"
      },
      {
        "lineNumber": 138,
        "author": {
          "gitId": "itskesin"
        },
        "content": "        fw.close();"
      },
      {
        "lineNumber": 139,
        "author": {
          "gitId": "itskesin"
        },
        "content": "    }"
      },
      {
        "lineNumber": 140,
        "author": {
          "gitId": "itskesin"
        },
        "content": ""
      },
      {
        "lineNumber": 141,
        "author": {
          "gitId": "itskesin"
        },
        "content": "    private static void printList(ArrayList\u003cTask\u003e tasks) {"
      },
      {
        "lineNumber": 142,
        "author": {
          "gitId": "itskesin"
        },
        "content": "        if (tasks.size() \u003d\u003d 0) {"
      },
      {
        "lineNumber": 143,
        "author": {
          "gitId": "itskesin"
        },
        "content": "            System.out.println(String.format(\"%50s\", \"YAYYYY! There are no tasks in your list \" + HAPPY_FACE));"
      },
      {
        "lineNumber": 144,
        "author": {
          "gitId": "itskesin"
        },
        "content": "            System.out.println(DIVIDER);"
      },
      {
        "lineNumber": 145,
        "author": {
          "gitId": "itskesin"
        },
        "content": "            return;"
      },
      {
        "lineNumber": 146,
        "author": {
          "gitId": "itskesin"
        },
        "content": "        }"
      },
      {
        "lineNumber": 147,
        "author": {
          "gitId": "itskesin"
        },
        "content": "        System.out.println(String.format(\"%50s\", \"Here are the tasks in your list:\"));"
      },
      {
        "lineNumber": 148,
        "author": {
          "gitId": "itskesin"
        },
        "content": "        for (int i \u003d 1; i \u003c\u003d tasks.size(); i++) { //is it better to start from 0 ?"
      },
      {
        "lineNumber": 149,
        "author": {
          "gitId": "itskesin"
        },
        "content": "            System.out.println(String.format(\"%50s\", i + \". \" + tasks.get(i-1)));"
      },
      {
        "lineNumber": 150,
        "author": {
          "gitId": "itskesin"
        },
        "content": "        }"
      },
      {
        "lineNumber": 151,
        "author": {
          "gitId": "itskesin"
        },
        "content": "        System.out.println(DIVIDER);"
      },
      {
        "lineNumber": 152,
        "author": {
          "gitId": "itskesin"
        },
        "content": "    }"
      },
      {
        "lineNumber": 153,
        "author": {
          "gitId": "itskesin"
        },
        "content": ""
      },
      {
        "lineNumber": 154,
        "author": {
          "gitId": "itskesin"
        },
        "content": "    private static void addDeadline(ArrayList\u003cTask\u003e tasks, String parseInput) {"
      },
      {
        "lineNumber": 155,
        "author": {
          "gitId": "itskesin"
        },
        "content": "        try {"
      },
      {
        "lineNumber": 156,
        "author": {
          "gitId": "itskesin"
        },
        "content": "            String[] deadline;"
      },
      {
        "lineNumber": 157,
        "author": {
          "gitId": "itskesin"
        },
        "content": "            deadline \u003d parseInput.split(\"/by\", 2);"
      },
      {
        "lineNumber": 158,
        "author": {
          "gitId": "itskesin"
        },
        "content": "            deadline[0] \u003d deadline[0].trim();"
      },
      {
        "lineNumber": 159,
        "author": {
          "gitId": "itskesin"
        },
        "content": "            if (!deadline[0].isEmpty()) {"
      },
      {
        "lineNumber": 160,
        "author": {
          "gitId": "itskesin"
        },
        "content": "                String time \u003d deadline[1].trim();"
      },
      {
        "lineNumber": 161,
        "author": {
          "gitId": "itskesin"
        },
        "content": "                if (time.isEmpty()) {"
      },
      {
        "lineNumber": 162,
        "author": {
          "gitId": "itskesin"
        },
        "content": "                    System.out.println(String.format(\"%50s\", SAD_FACE + \" Oops! Information is incomplete.\"));"
      },
      {
        "lineNumber": 163,
        "author": {
          "gitId": "itskesin"
        },
        "content": "                    System.out.println(DIVIDER);"
      },
      {
        "lineNumber": 164,
        "author": {
          "gitId": "itskesin"
        },
        "content": "                }"
      },
      {
        "lineNumber": 165,
        "author": {
          "gitId": "itskesin"
        },
        "content": "                tasks.add(new Deadline(deadline[0], time));"
      },
      {
        "lineNumber": 166,
        "author": {
          "gitId": "itskesin"
        },
        "content": "                System.out.println(String.format(\"%50s\", \"Got it. I\u0027ve added this deadline:\"));"
      },
      {
        "lineNumber": 167,
        "author": {
          "gitId": "itskesin"
        },
        "content": "                System.out.println(String.format(\"%50s\", tasks.get(tasks.size()-1)));"
      },
      {
        "lineNumber": 168,
        "author": {
          "gitId": "itskesin"
        },
        "content": "                System.out.println(String.format(\"\\n%50s\", tasks.size() + \" tasks in the list \" + SAD_FACE));"
      },
      {
        "lineNumber": 169,
        "author": {
          "gitId": "itskesin"
        },
        "content": "                System.out.println(DIVIDER);"
      },
      {
        "lineNumber": 170,
        "author": {
          "gitId": "itskesin"
        },
        "content": "            } else {"
      },
      {
        "lineNumber": 171,
        "author": {
          "gitId": "itskesin"
        },
        "content": "                //catch empty string"
      },
      {
        "lineNumber": 172,
        "author": {
          "gitId": "itskesin"
        },
        "content": "                throw new DukeException();"
      },
      {
        "lineNumber": 173,
        "author": {
          "gitId": "itskesin"
        },
        "content": "            }"
      },
      {
        "lineNumber": 174,
        "author": {
          "gitId": "itskesin"
        },
        "content": "        } catch (ArrayIndexOutOfBoundsException e) {"
      },
      {
        "lineNumber": 175,
        "author": {
          "gitId": "itskesin"
        },
        "content": "            System.out.println(String.format(\"%50s\", \"Oops! Please include /by follows by the date \" + SAD_FACE));"
      },
      {
        "lineNumber": 176,
        "author": {
          "gitId": "itskesin"
        },
        "content": "            System.out.println(DIVIDER);"
      },
      {
        "lineNumber": 177,
        "author": {
          "gitId": "itskesin"
        },
        "content": "        } catch (DukeException e) {"
      },
      {
        "lineNumber": 178,
        "author": {
          "gitId": "itskesin"
        },
        "content": "            System.out.println(String.format(\"%50s\", SAD_FACE + \" Oops! Information is incomplete.\"));"
      },
      {
        "lineNumber": 179,
        "author": {
          "gitId": "itskesin"
        },
        "content": "            System.out.println(DIVIDER);"
      },
      {
        "lineNumber": 180,
        "author": {
          "gitId": "itskesin"
        },
        "content": "        }"
      },
      {
        "lineNumber": 181,
        "author": {
          "gitId": "itskesin"
        },
        "content": "    }"
      },
      {
        "lineNumber": 182,
        "author": {
          "gitId": "itskesin"
        },
        "content": ""
      },
      {
        "lineNumber": 183,
        "author": {
          "gitId": "itskesin"
        },
        "content": "    private static void addEvent(ArrayList\u003cTask\u003e tasks, String parseInput) {"
      },
      {
        "lineNumber": 184,
        "author": {
          "gitId": "itskesin"
        },
        "content": "        try {"
      },
      {
        "lineNumber": 185,
        "author": {
          "gitId": "itskesin"
        },
        "content": "            String[] event;"
      },
      {
        "lineNumber": 186,
        "author": {
          "gitId": "itskesin"
        },
        "content": "            event \u003d parseInput.split(\"/at\", 2);"
      },
      {
        "lineNumber": 187,
        "author": {
          "gitId": "itskesin"
        },
        "content": ""
      },
      {
        "lineNumber": 188,
        "author": {
          "gitId": "itskesin"
        },
        "content": "            event[0] \u003d event[0].trim();"
      },
      {
        "lineNumber": 189,
        "author": {
          "gitId": "itskesin"
        },
        "content": "            "
      },
      {
        "lineNumber": 190,
        "author": {
          "gitId": "itskesin"
        },
        "content": "            if (!event[0].isEmpty()) {"
      },
      {
        "lineNumber": 191,
        "author": {
          "gitId": "itskesin"
        },
        "content": "                String time \u003d event[1].trim();"
      },
      {
        "lineNumber": 192,
        "author": {
          "gitId": "itskesin"
        },
        "content": "                if (time.isEmpty()) {"
      },
      {
        "lineNumber": 193,
        "author": {
          "gitId": "itskesin"
        },
        "content": "                    System.out.println(String.format(\"%50s\", SAD_FACE + \" Oops! Information is incomplete.\"));"
      },
      {
        "lineNumber": 194,
        "author": {
          "gitId": "itskesin"
        },
        "content": "                    System.out.println(DIVIDER);"
      },
      {
        "lineNumber": 195,
        "author": {
          "gitId": "itskesin"
        },
        "content": "                }"
      },
      {
        "lineNumber": 196,
        "author": {
          "gitId": "itskesin"
        },
        "content": "                tasks.add(new Event(event[0], time));"
      },
      {
        "lineNumber": 197,
        "author": {
          "gitId": "itskesin"
        },
        "content": "                System.out.println(String.format(\"%50s\", \"Got it. I\u0027ve added this event:\"));"
      },
      {
        "lineNumber": 198,
        "author": {
          "gitId": "itskesin"
        },
        "content": "                System.out.println(String.format(\"%50s\", tasks.get(tasks.size()-1)));"
      },
      {
        "lineNumber": 199,
        "author": {
          "gitId": "itskesin"
        },
        "content": "                System.out.println(String.format(\"\\n%50s\", tasks.size() + \" tasks in the list \" + SAD_FACE));"
      },
      {
        "lineNumber": 200,
        "author": {
          "gitId": "itskesin"
        },
        "content": "                System.out.println(DIVIDER);"
      },
      {
        "lineNumber": 201,
        "author": {
          "gitId": "itskesin"
        },
        "content": "            } else {"
      },
      {
        "lineNumber": 202,
        "author": {
          "gitId": "itskesin"
        },
        "content": "                //catch empty string"
      },
      {
        "lineNumber": 203,
        "author": {
          "gitId": "itskesin"
        },
        "content": "                throw new DukeException();"
      },
      {
        "lineNumber": 204,
        "author": {
          "gitId": "itskesin"
        },
        "content": "            }"
      },
      {
        "lineNumber": 205,
        "author": {
          "gitId": "itskesin"
        },
        "content": "        } catch (ArrayIndexOutOfBoundsException e) {"
      },
      {
        "lineNumber": 206,
        "author": {
          "gitId": "itskesin"
        },
        "content": "            System.out.println(String.format(\"%50s\", \"Oops! Please include /at follows by the date \" + SAD_FACE));"
      },
      {
        "lineNumber": 207,
        "author": {
          "gitId": "itskesin"
        },
        "content": "            System.out.println(DIVIDER);"
      },
      {
        "lineNumber": 208,
        "author": {
          "gitId": "itskesin"
        },
        "content": "        } catch (DukeException e) {"
      },
      {
        "lineNumber": 209,
        "author": {
          "gitId": "itskesin"
        },
        "content": "            System.out.println(String.format(\"%50s\", SAD_FACE + \" Oops! Information is incomplete.\"));"
      },
      {
        "lineNumber": 210,
        "author": {
          "gitId": "itskesin"
        },
        "content": "            System.out.println(DIVIDER);"
      },
      {
        "lineNumber": 211,
        "author": {
          "gitId": "itskesin"
        },
        "content": "        }"
      },
      {
        "lineNumber": 212,
        "author": {
          "gitId": "itskesin"
        },
        "content": "    }"
      },
      {
        "lineNumber": 213,
        "author": {
          "gitId": "itskesin"
        },
        "content": ""
      },
      {
        "lineNumber": 214,
        "author": {
          "gitId": "itskesin"
        },
        "content": "    private static void addToDo(ArrayList\u003cTask\u003e tasks, String[] parseInput) {"
      },
      {
        "lineNumber": 215,
        "author": {
          "gitId": "itskesin"
        },
        "content": "        try {"
      },
      {
        "lineNumber": 216,
        "author": {
          "gitId": "itskesin"
        },
        "content": "            if (!parseInput[1].isEmpty()) {"
      },
      {
        "lineNumber": 217,
        "author": {
          "gitId": "itskesin"
        },
        "content": "                tasks.add(new ToDo(parseInput[1]));"
      },
      {
        "lineNumber": 218,
        "author": {
          "gitId": "itskesin"
        },
        "content": "                System.out.println(String.format(\"%50s\", \"Got it. I\u0027ve added this task:\"));"
      },
      {
        "lineNumber": 219,
        "author": {
          "gitId": "itskesin"
        },
        "content": "                System.out.println(String.format(\"%50s\", tasks.get(tasks.size()-1)));"
      },
      {
        "lineNumber": 220,
        "author": {
          "gitId": "itskesin"
        },
        "content": "                System.out.println(String.format(\"\\n%50s\", tasks.size() + \" tasks in the list \" + SAD_FACE));"
      },
      {
        "lineNumber": 221,
        "author": {
          "gitId": "itskesin"
        },
        "content": "                System.out.println(DIVIDER);"
      },
      {
        "lineNumber": 222,
        "author": {
          "gitId": "itskesin"
        },
        "content": "            } else {"
      },
      {
        "lineNumber": 223,
        "author": {
          "gitId": "itskesin"
        },
        "content": "                throw new DukeException();"
      },
      {
        "lineNumber": 224,
        "author": {
          "gitId": "itskesin"
        },
        "content": "            }"
      },
      {
        "lineNumber": 225,
        "author": {
          "gitId": "itskesin"
        },
        "content": "        } catch (ArrayIndexOutOfBoundsException e) {"
      },
      {
        "lineNumber": 226,
        "author": {
          "gitId": "itskesin"
        },
        "content": "            System.out.println(String.format(\"%50s\", SAD_FACE + \" Oops! Information is incomplete.\"));"
      },
      {
        "lineNumber": 227,
        "author": {
          "gitId": "itskesin"
        },
        "content": "            System.out.println(DIVIDER);"
      },
      {
        "lineNumber": 228,
        "author": {
          "gitId": "itskesin"
        },
        "content": "        } catch (DukeException e) {"
      },
      {
        "lineNumber": 229,
        "author": {
          "gitId": "itskesin"
        },
        "content": "            System.out.println(String.format(\"%50s\", \"Please include task description. \" + SAD_FACE));"
      },
      {
        "lineNumber": 230,
        "author": {
          "gitId": "itskesin"
        },
        "content": "            System.out.println(DIVIDER);"
      },
      {
        "lineNumber": 231,
        "author": {
          "gitId": "itskesin"
        },
        "content": "        }"
      },
      {
        "lineNumber": 232,
        "author": {
          "gitId": "itskesin"
        },
        "content": "    }"
      },
      {
        "lineNumber": 233,
        "author": {
          "gitId": "itskesin"
        },
        "content": ""
      },
      {
        "lineNumber": 234,
        "author": {
          "gitId": "itskesin"
        },
        "content": "    private static void printDoneTasks(ArrayList\u003cTask\u003e tasks, String s) {"
      },
      {
        "lineNumber": 235,
        "author": {
          "gitId": "itskesin"
        },
        "content": "        try {"
      },
      {
        "lineNumber": 236,
        "author": {
          "gitId": "itskesin"
        },
        "content": "            int doneTask \u003d Integer.parseInt(s)-1;"
      },
      {
        "lineNumber": 237,
        "author": {
          "gitId": "itskesin"
        },
        "content": "            tasks.get(doneTask).updateTask();"
      },
      {
        "lineNumber": 238,
        "author": {
          "gitId": "itskesin"
        },
        "content": "            System.out.println(String.format(\"%50s\", \"Nice! I\u0027ve marked this task as done:\"));"
      },
      {
        "lineNumber": 239,
        "author": {
          "gitId": "itskesin"
        },
        "content": "            System.out.println(String.format(\"%50s\", tasks.get(doneTask)));"
      },
      {
        "lineNumber": 240,
        "author": {
          "gitId": "itskesin"
        },
        "content": "            System.out.println(DIVIDER);"
      },
      {
        "lineNumber": 241,
        "author": {
          "gitId": "itskesin"
        },
        "content": "        } catch (IndexOutOfBoundsException e) {"
      },
      {
        "lineNumber": 242,
        "author": {
          "gitId": "itskesin"
        },
        "content": "            System.out.println(String.format(\"Task not included in the list, please try again.\"));"
      },
      {
        "lineNumber": 243,
        "author": {
          "gitId": "itskesin"
        },
        "content": "            System.out.println(DIVIDER);"
      },
      {
        "lineNumber": 244,
        "author": {
          "gitId": "itskesin"
        },
        "content": "        } catch (Exception e) {"
      },
      {
        "lineNumber": 245,
        "author": {
          "gitId": "itskesin"
        },
        "content": "            //done + empty string/invalid input"
      },
      {
        "lineNumber": 246,
        "author": {
          "gitId": "itskesin"
        },
        "content": "            System.out.println(String.format(\"%50s\", SAD_FACE + \" Oops! Information is incomplete.\"));"
      },
      {
        "lineNumber": 247,
        "author": {
          "gitId": "itskesin"
        },
        "content": "            System.out.println(DIVIDER);"
      },
      {
        "lineNumber": 248,
        "author": {
          "gitId": "itskesin"
        },
        "content": "        }"
      },
      {
        "lineNumber": 249,
        "author": {
          "gitId": "itskesin"
        },
        "content": "    }"
      },
      {
        "lineNumber": 250,
        "author": {
          "gitId": "itskesin"
        },
        "content": ""
      },
      {
        "lineNumber": 251,
        "author": {
          "gitId": "itskesin"
        },
        "content": "    private static void printByeMessage(String name) {"
      },
      {
        "lineNumber": 252,
        "author": {
          "gitId": "itskesin"
        },
        "content": "        System.out.println(String.format(\"%50s\", \"Bye, \" + name + \". Hope to see you again soon!\"));"
      },
      {
        "lineNumber": 253,
        "author": {
          "gitId": "itskesin"
        },
        "content": "        System.out.println(DIVIDER);"
      },
      {
        "lineNumber": 254,
        "author": {
          "gitId": "itskesin"
        },
        "content": "    }"
      },
      {
        "lineNumber": 255,
        "author": {
          "gitId": "itskesin"
        },
        "content": ""
      },
      {
        "lineNumber": 256,
        "author": {
          "gitId": "itskesin"
        },
        "content": "    private static void printUserGreeting(String name) {"
      },
      {
        "lineNumber": 257,
        "author": {
          "gitId": "itskesin"
        },
        "content": "        System.out.println(DIVIDER);"
      },
      {
        "lineNumber": 258,
        "author": {
          "gitId": "itskesin"
        },
        "content": "        System.out.println(String.format(\"%50s\", \"Hello \" + name + \", Anything I can help you with?\"));"
      },
      {
        "lineNumber": 259,
        "author": {
          "gitId": "itskesin"
        },
        "content": "        System.out.println(DIVIDER);"
      },
      {
        "lineNumber": 260,
        "author": {
          "gitId": "itskesin"
        },
        "content": "    }"
      },
      {
        "lineNumber": 261,
        "author": {
          "gitId": "itskesin"
        },
        "content": ""
      },
      {
        "lineNumber": 262,
        "author": {
          "gitId": "itskesin"
        },
        "content": "    private static void printWelcomeMessage() {"
      },
      {
        "lineNumber": 263,
        "author": {
          "gitId": "itskesin"
        },
        "content": "        String logo \u003d \" /$$   /$$                     /$$\\n\""
      },
      {
        "lineNumber": 264,
        "author": {
          "gitId": "itskesin"
        },
        "content": "                + \"| $$  /$$/                    |__/\\n\""
      },
      {
        "lineNumber": 265,
        "author": {
          "gitId": "itskesin"
        },
        "content": "                + \"| $$ /$$/   /$$$$$$   /$$$$$$$ /$$ /$$$$$$$\\n\""
      },
      {
        "lineNumber": 266,
        "author": {
          "gitId": "itskesin"
        },
        "content": "                + \"| $$$$$/   /$$__  $$ /$$_____/| $$| $$__  $$\\n\""
      },
      {
        "lineNumber": 267,
        "author": {
          "gitId": "itskesin"
        },
        "content": "                + \"| $$  $$  | $$$$$$$$|  $$$$$$ | $$| $$  \\\\ $$\\n\""
      },
      {
        "lineNumber": 268,
        "author": {
          "gitId": "itskesin"
        },
        "content": "                + \"| $$\\\\  $$ | $$_____/ \\\\____  $$| $$| $$  | $$\\n\""
      },
      {
        "lineNumber": 269,
        "author": {
          "gitId": "itskesin"
        },
        "content": "                + \"| $$ \\\\  $$|  $$$$$$$ /$$$$$$$/| $$| $$  | $$\\n\""
      },
      {
        "lineNumber": 270,
        "author": {
          "gitId": "itskesin"
        },
        "content": "                + \"|__/  \\\\__/ \\\\_______/|_______/ |__/|__/  |__/\";"
      },
      {
        "lineNumber": 271,
        "author": {
          "gitId": "itskesin"
        },
        "content": ""
      },
      {
        "lineNumber": 272,
        "author": {
          "gitId": "itskesin"
        },
        "content": "        System.out.println(\"Hello from\\n\" + logo);"
      },
      {
        "lineNumber": 273,
        "author": {
          "gitId": "itskesin"
        },
        "content": "        System.out.println(DIVIDER);"
      },
      {
        "lineNumber": 274,
        "author": {
          "gitId": "itskesin"
        },
        "content": "        String s1 \u003d String.format(\"%50s\", \"What\u0027s your name?\");"
      },
      {
        "lineNumber": 275,
        "author": {
          "gitId": "itskesin"
        },
        "content": "        System.out.println(s1);"
      },
      {
        "lineNumber": 276,
        "author": {
          "gitId": "-"
        },
        "content": "    }"
      },
      {
        "lineNumber": 277,
        "author": {
          "gitId": "-"
        },
        "content": "}"
      }
    ],
    "authorContributionMap": {
      "itskesin": 273,
      "-": 4
    }
  },
  {
    "path": "src/main/java/duke/DukeException.java",
    "fileType": "java",
    "lines": [
      {
        "lineNumber": 1,
        "author": {
          "gitId": "itskesin"
        },
        "content": "package duke;"
      },
      {
        "lineNumber": 2,
        "author": {
          "gitId": "itskesin"
        },
        "content": ""
      },
      {
        "lineNumber": 3,
        "author": {
          "gitId": "itskesin"
        },
        "content": "public class DukeException extends Exception {"
      },
      {
        "lineNumber": 4,
        "author": {
          "gitId": "itskesin"
        },
        "content": ""
      },
      {
        "lineNumber": 5,
        "author": {
          "gitId": "itskesin"
        },
        "content": "}"
      }
    ],
    "authorContributionMap": {
      "itskesin": 5
    }
  },
  {
    "path": "src/main/java/duke/task/Deadline.java",
    "fileType": "java",
    "lines": [
      {
        "lineNumber": 1,
        "author": {
          "gitId": "itskesin"
        },
        "content": "package duke.task;"
      },
      {
        "lineNumber": 2,
        "author": {
          "gitId": "itskesin"
        },
        "content": ""
      },
      {
        "lineNumber": 3,
        "author": {
          "gitId": "itskesin"
        },
        "content": "public class Deadline extends Task {"
      },
      {
        "lineNumber": 4,
        "author": {
          "gitId": "itskesin"
        },
        "content": ""
      },
      {
        "lineNumber": 5,
        "author": {
          "gitId": "itskesin"
        },
        "content": "    protected String by;"
      },
      {
        "lineNumber": 6,
        "author": {
          "gitId": "itskesin"
        },
        "content": "    public Deadline(String description, String by) {"
      },
      {
        "lineNumber": 7,
        "author": {
          "gitId": "itskesin"
        },
        "content": "        super(description);"
      },
      {
        "lineNumber": 8,
        "author": {
          "gitId": "itskesin"
        },
        "content": "        this.by \u003d by;"
      },
      {
        "lineNumber": 9,
        "author": {
          "gitId": "itskesin"
        },
        "content": "    }"
      },
      {
        "lineNumber": 10,
        "author": {
          "gitId": "itskesin"
        },
        "content": ""
      },
      {
        "lineNumber": 11,
        "author": {
          "gitId": "itskesin"
        },
        "content": "    @Override"
      },
      {
        "lineNumber": 12,
        "author": {
          "gitId": "itskesin"
        },
        "content": "    public String saveTask() {"
      },
      {
        "lineNumber": 13,
        "author": {
          "gitId": "itskesin"
        },
        "content": "        return \"D | \" + (super.isDone ? 1 : 0) + \" | \" + super.description + \" | \" + by;"
      },
      {
        "lineNumber": 14,
        "author": {
          "gitId": "itskesin"
        },
        "content": "    }"
      },
      {
        "lineNumber": 15,
        "author": {
          "gitId": "itskesin"
        },
        "content": ""
      },
      {
        "lineNumber": 16,
        "author": {
          "gitId": "itskesin"
        },
        "content": "    @Override"
      },
      {
        "lineNumber": 17,
        "author": {
          "gitId": "itskesin"
        },
        "content": "    public String toString() {"
      },
      {
        "lineNumber": 18,
        "author": {
          "gitId": "itskesin"
        },
        "content": "        return \"[D]\" + super.toString() + \"(by:\" + by + \")\";"
      },
      {
        "lineNumber": 19,
        "author": {
          "gitId": "itskesin"
        },
        "content": "    }"
      },
      {
        "lineNumber": 20,
        "author": {
          "gitId": "itskesin"
        },
        "content": "}"
      }
    ],
    "authorContributionMap": {
      "itskesin": 20
    }
  },
  {
    "path": "src/main/java/duke/task/Event.java",
    "fileType": "java",
    "lines": [
      {
        "lineNumber": 1,
        "author": {
          "gitId": "itskesin"
        },
        "content": "package duke.task;"
      },
      {
        "lineNumber": 2,
        "author": {
          "gitId": "itskesin"
        },
        "content": ""
      },
      {
        "lineNumber": 3,
        "author": {
          "gitId": "itskesin"
        },
        "content": "public class Event extends Task {"
      },
      {
        "lineNumber": 4,
        "author": {
          "gitId": "itskesin"
        },
        "content": ""
      },
      {
        "lineNumber": 5,
        "author": {
          "gitId": "itskesin"
        },
        "content": "    protected String at;"
      },
      {
        "lineNumber": 6,
        "author": {
          "gitId": "itskesin"
        },
        "content": "    public Event(String description, String at) {"
      },
      {
        "lineNumber": 7,
        "author": {
          "gitId": "itskesin"
        },
        "content": "        super(description);"
      },
      {
        "lineNumber": 8,
        "author": {
          "gitId": "itskesin"
        },
        "content": "        this.at \u003d at;"
      },
      {
        "lineNumber": 9,
        "author": {
          "gitId": "itskesin"
        },
        "content": "    }"
      },
      {
        "lineNumber": 10,
        "author": {
          "gitId": "itskesin"
        },
        "content": ""
      },
      {
        "lineNumber": 11,
        "author": {
          "gitId": "itskesin"
        },
        "content": "    @Override"
      },
      {
        "lineNumber": 12,
        "author": {
          "gitId": "itskesin"
        },
        "content": "    public String saveTask() {"
      },
      {
        "lineNumber": 13,
        "author": {
          "gitId": "itskesin"
        },
        "content": "        return \"E | \" + (super.isDone ? 1 : 0) + \" | \" + super.description + \" | \" + at;"
      },
      {
        "lineNumber": 14,
        "author": {
          "gitId": "itskesin"
        },
        "content": "    }"
      },
      {
        "lineNumber": 15,
        "author": {
          "gitId": "itskesin"
        },
        "content": ""
      },
      {
        "lineNumber": 16,
        "author": {
          "gitId": "itskesin"
        },
        "content": "    @Override"
      },
      {
        "lineNumber": 17,
        "author": {
          "gitId": "itskesin"
        },
        "content": "    public String toString() {"
      },
      {
        "lineNumber": 18,
        "author": {
          "gitId": "itskesin"
        },
        "content": "        return \"[E]\" + super.toString() + \"(at:\" + at + \")\";"
      },
      {
        "lineNumber": 19,
        "author": {
          "gitId": "itskesin"
        },
        "content": "    }"
      },
      {
        "lineNumber": 20,
        "author": {
          "gitId": "itskesin"
        },
        "content": "}"
      }
    ],
    "authorContributionMap": {
      "itskesin": 20
    }
  },
  {
    "path": "src/main/java/duke/task/Task.java",
    "fileType": "java",
    "lines": [
      {
        "lineNumber": 1,
        "author": {
          "gitId": "itskesin"
        },
        "content": "package duke.task;"
      },
      {
        "lineNumber": 2,
        "author": {
          "gitId": "itskesin"
        },
        "content": ""
      },
      {
        "lineNumber": 3,
        "author": {
          "gitId": "itskesin"
        },
        "content": "public abstract class Task {"
      },
      {
        "lineNumber": 4,
        "author": {
          "gitId": "itskesin"
        },
        "content": ""
      },
      {
        "lineNumber": 5,
        "author": {
          "gitId": "itskesin"
        },
        "content": "    protected String description;"
      },
      {
        "lineNumber": 6,
        "author": {
          "gitId": "itskesin"
        },
        "content": "    protected boolean isDone;"
      },
      {
        "lineNumber": 7,
        "author": {
          "gitId": "itskesin"
        },
        "content": ""
      },
      {
        "lineNumber": 8,
        "author": {
          "gitId": "itskesin"
        },
        "content": "    public Task(String description) {"
      },
      {
        "lineNumber": 9,
        "author": {
          "gitId": "itskesin"
        },
        "content": "        this.description \u003d description;"
      },
      {
        "lineNumber": 10,
        "author": {
          "gitId": "itskesin"
        },
        "content": "        this.isDone \u003d false;"
      },
      {
        "lineNumber": 11,
        "author": {
          "gitId": "itskesin"
        },
        "content": "    }"
      },
      {
        "lineNumber": 12,
        "author": {
          "gitId": "itskesin"
        },
        "content": ""
      },
      {
        "lineNumber": 13,
        "author": {
          "gitId": "itskesin"
        },
        "content": "    public String getStatusIcon() {"
      },
      {
        "lineNumber": 14,
        "author": {
          "gitId": "itskesin"
        },
        "content": "        return (isDone ? \"\\u2713\" : \"\\u2718\"); //return tick or X symbols"
      },
      {
        "lineNumber": 15,
        "author": {
          "gitId": "itskesin"
        },
        "content": "    }"
      },
      {
        "lineNumber": 16,
        "author": {
          "gitId": "itskesin"
        },
        "content": ""
      },
      {
        "lineNumber": 17,
        "author": {
          "gitId": "itskesin"
        },
        "content": "    public void updateTask() {"
      },
      {
        "lineNumber": 18,
        "author": {
          "gitId": "itskesin"
        },
        "content": "        this.isDone \u003d true;"
      },
      {
        "lineNumber": 19,
        "author": {
          "gitId": "itskesin"
        },
        "content": "    }"
      },
      {
        "lineNumber": 20,
        "author": {
          "gitId": "itskesin"
        },
        "content": ""
      },
      {
        "lineNumber": 21,
        "author": {
          "gitId": "itskesin"
        },
        "content": "    public abstract String saveTask();"
      },
      {
        "lineNumber": 22,
        "author": {
          "gitId": "itskesin"
        },
        "content": ""
      },
      {
        "lineNumber": 23,
        "author": {
          "gitId": "itskesin"
        },
        "content": "    public String toString() {"
      },
      {
        "lineNumber": 24,
        "author": {
          "gitId": "itskesin"
        },
        "content": "        return \"[\" + this.getStatusIcon() + \"] \" + description;"
      },
      {
        "lineNumber": 25,
        "author": {
          "gitId": "itskesin"
        },
        "content": "    }"
      },
      {
        "lineNumber": 26,
        "author": {
          "gitId": "itskesin"
        },
        "content": "}"
      }
    ],
    "authorContributionMap": {
      "itskesin": 26
    }
  },
  {
    "path": "src/main/java/duke/task/ToDo.java",
    "fileType": "java",
    "lines": [
      {
        "lineNumber": 1,
        "author": {
          "gitId": "itskesin"
        },
        "content": "package duke.task;"
      },
      {
        "lineNumber": 2,
        "author": {
          "gitId": "itskesin"
        },
        "content": ""
      },
      {
        "lineNumber": 3,
        "author": {
          "gitId": "itskesin"
        },
        "content": "public class ToDo extends Task {"
      },
      {
        "lineNumber": 4,
        "author": {
          "gitId": "itskesin"
        },
        "content": ""
      },
      {
        "lineNumber": 5,
        "author": {
          "gitId": "itskesin"
        },
        "content": "    public ToDo(String description) {"
      },
      {
        "lineNumber": 6,
        "author": {
          "gitId": "itskesin"
        },
        "content": "        super(description);"
      },
      {
        "lineNumber": 7,
        "author": {
          "gitId": "itskesin"
        },
        "content": "    }"
      },
      {
        "lineNumber": 8,
        "author": {
          "gitId": "itskesin"
        },
        "content": ""
      },
      {
        "lineNumber": 9,
        "author": {
          "gitId": "itskesin"
        },
        "content": "    @Override"
      },
      {
        "lineNumber": 10,
        "author": {
          "gitId": "itskesin"
        },
        "content": "    public String saveTask() {"
      },
      {
        "lineNumber": 11,
        "author": {
          "gitId": "itskesin"
        },
        "content": "        return \"T | \" + (super.isDone ? 1 : 0) + \" | \" + super.description;"
      },
      {
        "lineNumber": 12,
        "author": {
          "gitId": "itskesin"
        },
        "content": "    }"
      },
      {
        "lineNumber": 13,
        "author": {
          "gitId": "itskesin"
        },
        "content": ""
      },
      {
        "lineNumber": 14,
        "author": {
          "gitId": "itskesin"
        },
        "content": "    @Override"
      },
      {
        "lineNumber": 15,
        "author": {
          "gitId": "itskesin"
        },
        "content": "    public String toString() {"
      },
      {
        "lineNumber": 16,
        "author": {
          "gitId": "itskesin"
        },
        "content": "        return \"[T]\" + super.toString();"
      },
      {
        "lineNumber": 17,
        "author": {
          "gitId": "itskesin"
        },
        "content": "    }"
      },
      {
        "lineNumber": 18,
        "author": {
          "gitId": "itskesin"
        },
        "content": "}"
      }
    ],
    "authorContributionMap": {
      "itskesin": 18
    }
  },
  {
    "path": "test-ui-test/EXPECTED.txt",
    "fileType": "txt",
    "lines": [
      {
        "lineNumber": 1,
        "author": {
          "gitId": "itskesin"
        },
        "content": "Hello from"
      },
      {
        "lineNumber": 2,
        "author": {
          "gitId": "itskesin"
        },
        "content": " /$$   /$$                     /$$"
      },
      {
        "lineNumber": 3,
        "author": {
          "gitId": "itskesin"
        },
        "content": "| $$  /$$/                    |__/"
      },
      {
        "lineNumber": 4,
        "author": {
          "gitId": "itskesin"
        },
        "content": "| $$ /$$/   /$$$$$$   /$$$$$$$ /$$ /$$$$$$$"
      },
      {
        "lineNumber": 5,
        "author": {
          "gitId": "itskesin"
        },
        "content": "| $$$$$/   /$$__  $$ /$$_____/| $$| $$__  $$"
      },
      {
        "lineNumber": 6,
        "author": {
          "gitId": "itskesin"
        },
        "content": "| $$  $$  | $$$$$$$$|  $$$$$$ | $$| $$  \\ $$"
      },
      {
        "lineNumber": 7,
        "author": {
          "gitId": "itskesin"
        },
        "content": "| $$\\  $$ | $$_____/ \\____  $$| $$| $$  | $$"
      },
      {
        "lineNumber": 8,
        "author": {
          "gitId": "itskesin"
        },
        "content": "| $$ \\  $$|  $$$$$$$ /$$$$$$$/| $$| $$  | $$"
      },
      {
        "lineNumber": 9,
        "author": {
          "gitId": "itskesin"
        },
        "content": "|__/  \\__/ \\_______/|_______/ |__/|__/  |__/"
      },
      {
        "lineNumber": 10,
        "author": {
          "gitId": "itskesin"
        },
        "content": "\u003d\u003d\u003d\u003d\u003d\u003d\u003d\u003d\u003d\u003d\u003d\u003d\u003d\u003d\u003d\u003d\u003d\u003d\u003d\u003d\u003d\u003d\u003d\u003d\u003d\u003d\u003d\u003d\u003d\u003d\u003d\u003d\u003d\u003d\u003d\u003d\u003d\u003d\u003d\u003d\u003d\u003d\u003d\u003d\u003d\u003d\u003d\u003d\u003d\u003d\u003d"
      },
      {
        "lineNumber": 11,
        "author": {
          "gitId": "itskesin"
        },
        "content": "                                 What\u0027s your name?"
      },
      {
        "lineNumber": 12,
        "author": {
          "gitId": "itskesin"
        },
        "content": "\u003d\u003d\u003d\u003d\u003d\u003d\u003d\u003d\u003d\u003d\u003d\u003d\u003d\u003d\u003d\u003d\u003d\u003d\u003d\u003d\u003d\u003d\u003d\u003d\u003d\u003d\u003d\u003d\u003d\u003d\u003d\u003d\u003d\u003d\u003d\u003d\u003d\u003d\u003d\u003d\u003d\u003d\u003d\u003d\u003d\u003d\u003d\u003d\u003d\u003d\u003d"
      },
      {
        "lineNumber": 13,
        "author": {
          "gitId": "itskesin"
        },
        "content": "        Hello kesin, Anything I can help you with?"
      },
      {
        "lineNumber": 14,
        "author": {
          "gitId": "itskesin"
        },
        "content": "\u003d\u003d\u003d\u003d\u003d\u003d\u003d\u003d\u003d\u003d\u003d\u003d\u003d\u003d\u003d\u003d\u003d\u003d\u003d\u003d\u003d\u003d\u003d\u003d\u003d\u003d\u003d\u003d\u003d\u003d\u003d\u003d\u003d\u003d\u003d\u003d\u003d\u003d\u003d\u003d\u003d\u003d\u003d\u003d\u003d\u003d\u003d\u003d\u003d\u003d\u003d"
      },
      {
        "lineNumber": 15,
        "author": {
          "gitId": "itskesin"
        },
        "content": "                     Got it. I\u0027ve added this task:"
      },
      {
        "lineNumber": 16,
        "author": {
          "gitId": "itskesin"
        },
        "content": "                                [T][✘] borrow book"
      },
      {
        "lineNumber": 17,
        "author": {
          "gitId": "itskesin"
        },
        "content": ""
      },
      {
        "lineNumber": 18,
        "author": {
          "gitId": "itskesin"
        },
        "content": "                     1 tasks in the list (â•¥_â•¥)"
      },
      {
        "lineNumber": 19,
        "author": {
          "gitId": "itskesin"
        },
        "content": "\u003d\u003d\u003d\u003d\u003d\u003d\u003d\u003d\u003d\u003d\u003d\u003d\u003d\u003d\u003d\u003d\u003d\u003d\u003d\u003d\u003d\u003d\u003d\u003d\u003d\u003d\u003d\u003d\u003d\u003d\u003d\u003d\u003d\u003d\u003d\u003d\u003d\u003d\u003d\u003d\u003d\u003d\u003d\u003d\u003d\u003d\u003d\u003d\u003d\u003d\u003d"
      },
      {
        "lineNumber": 20,
        "author": {
          "gitId": "itskesin"
        },
        "content": "         Oops! Information is incomplete (â•¥_â•¥)"
      },
      {
        "lineNumber": 21,
        "author": {
          "gitId": "itskesin"
        },
        "content": "\u003d\u003d\u003d\u003d\u003d\u003d\u003d\u003d\u003d\u003d\u003d\u003d\u003d\u003d\u003d\u003d\u003d\u003d\u003d\u003d\u003d\u003d\u003d\u003d\u003d\u003d\u003d\u003d\u003d\u003d\u003d\u003d\u003d\u003d\u003d\u003d\u003d\u003d\u003d\u003d\u003d\u003d\u003d\u003d\u003d\u003d\u003d\u003d\u003d\u003d\u003d"
      },
      {
        "lineNumber": 22,
        "author": {
          "gitId": "itskesin"
        },
        "content": "  Please include task number in the list (â•¥_â•¥)"
      },
      {
        "lineNumber": 23,
        "author": {
          "gitId": "itskesin"
        },
        "content": "\u003d\u003d\u003d\u003d\u003d\u003d\u003d\u003d\u003d\u003d\u003d\u003d\u003d\u003d\u003d\u003d\u003d\u003d\u003d\u003d\u003d\u003d\u003d\u003d\u003d\u003d\u003d\u003d\u003d\u003d\u003d\u003d\u003d\u003d\u003d\u003d\u003d\u003d\u003d\u003d\u003d\u003d\u003d\u003d\u003d\u003d\u003d\u003d\u003d\u003d\u003d"
      },
      {
        "lineNumber": 24,
        "author": {
          "gitId": "itskesin"
        },
        "content": "                 Got it. I\u0027ve added this deadline:"
      },
      {
        "lineNumber": 25,
        "author": {
          "gitId": "itskesin"
        },
        "content": "                   [D][✘] return book (by: Monday)"
      },
      {
        "lineNumber": 26,
        "author": {
          "gitId": "itskesin"
        },
        "content": ""
      },
      {
        "lineNumber": 27,
        "author": {
          "gitId": "itskesin"
        },
        "content": "                     2 tasks in the list (â•¥_â•¥)"
      },
      {
        "lineNumber": 28,
        "author": {
          "gitId": "itskesin"
        },
        "content": "\u003d\u003d\u003d\u003d\u003d\u003d\u003d\u003d\u003d\u003d\u003d\u003d\u003d\u003d\u003d\u003d\u003d\u003d\u003d\u003d\u003d\u003d\u003d\u003d\u003d\u003d\u003d\u003d\u003d\u003d\u003d\u003d\u003d\u003d\u003d\u003d\u003d\u003d\u003d\u003d\u003d\u003d\u003d\u003d\u003d\u003d\u003d\u003d\u003d\u003d\u003d"
      },
      {
        "lineNumber": 29,
        "author": {
          "gitId": "itskesin"
        },
        "content": "                     Got it. I\u0027ve added this task:"
      },
      {
        "lineNumber": 30,
        "author": {
          "gitId": "itskesin"
        },
        "content": "                                      [T][✘] study"
      },
      {
        "lineNumber": 31,
        "author": {
          "gitId": "itskesin"
        },
        "content": ""
      },
      {
        "lineNumber": 32,
        "author": {
          "gitId": "itskesin"
        },
        "content": "                     3 tasks in the list (â•¥_â•¥)"
      },
      {
        "lineNumber": 33,
        "author": {
          "gitId": "itskesin"
        },
        "content": "\u003d\u003d\u003d\u003d\u003d\u003d\u003d\u003d\u003d\u003d\u003d\u003d\u003d\u003d\u003d\u003d\u003d\u003d\u003d\u003d\u003d\u003d\u003d\u003d\u003d\u003d\u003d\u003d\u003d\u003d\u003d\u003d\u003d\u003d\u003d\u003d\u003d\u003d\u003d\u003d\u003d\u003d\u003d\u003d\u003d\u003d\u003d\u003d\u003d\u003d\u003d"
      },
      {
        "lineNumber": 34,
        "author": {
          "gitId": "itskesin"
        },
        "content": "              Nice! I\u0027ve marked this task as done:"
      },
      {
        "lineNumber": 35,
        "author": {
          "gitId": "itskesin"
        },
        "content": "                                [T][✓] borrow book"
      },
      {
        "lineNumber": 36,
        "author": {
          "gitId": "itskesin"
        },
        "content": "\u003d\u003d\u003d\u003d\u003d\u003d\u003d\u003d\u003d\u003d\u003d\u003d\u003d\u003d\u003d\u003d\u003d\u003d\u003d\u003d\u003d\u003d\u003d\u003d\u003d\u003d\u003d\u003d\u003d\u003d\u003d\u003d\u003d\u003d\u003d\u003d\u003d\u003d\u003d\u003d\u003d\u003d\u003d\u003d\u003d\u003d\u003d\u003d\u003d\u003d\u003d"
      },
      {
        "lineNumber": 37,
        "author": {
          "gitId": "itskesin"
        },
        "content": "Oops! Please include /by follows by the date (â•¥_â•¥)"
      },
      {
        "lineNumber": 38,
        "author": {
          "gitId": "itskesin"
        },
        "content": "\u003d\u003d\u003d\u003d\u003d\u003d\u003d\u003d\u003d\u003d\u003d\u003d\u003d\u003d\u003d\u003d\u003d\u003d\u003d\u003d\u003d\u003d\u003d\u003d\u003d\u003d\u003d\u003d\u003d\u003d\u003d\u003d\u003d\u003d\u003d\u003d\u003d\u003d\u003d\u003d\u003d\u003d\u003d\u003d\u003d\u003d\u003d\u003d\u003d\u003d\u003d"
      },
      {
        "lineNumber": 39,
        "author": {
          "gitId": "itskesin"
        },
        "content": "              Nice! I\u0027ve marked this task as done:"
      },
      {
        "lineNumber": 40,
        "author": {
          "gitId": "itskesin"
        },
        "content": "                   [D][✓] return book (by: Monday)"
      },
      {
        "lineNumber": 41,
        "author": {
          "gitId": "itskesin"
        },
        "content": "\u003d\u003d\u003d\u003d\u003d\u003d\u003d\u003d\u003d\u003d\u003d\u003d\u003d\u003d\u003d\u003d\u003d\u003d\u003d\u003d\u003d\u003d\u003d\u003d\u003d\u003d\u003d\u003d\u003d\u003d\u003d\u003d\u003d\u003d\u003d\u003d\u003d\u003d\u003d\u003d\u003d\u003d\u003d\u003d\u003d\u003d\u003d\u003d\u003d\u003d\u003d"
      },
      {
        "lineNumber": 42,
        "author": {
          "gitId": "itskesin"
        },
        "content": "                  Here are the tasks in your list:"
      },
      {
        "lineNumber": 43,
        "author": {
          "gitId": "itskesin"
        },
        "content": "                             1. [T][✓] borrow book"
      },
      {
        "lineNumber": 44,
        "author": {
          "gitId": "itskesin"
        },
        "content": "                2. [D][✓] return book (by: Monday)"
      },
      {
        "lineNumber": 45,
        "author": {
          "gitId": "itskesin"
        },
        "content": "                                   3. [T][✘] study"
      },
      {
        "lineNumber": 46,
        "author": {
          "gitId": "itskesin"
        },
        "content": "\u003d\u003d\u003d\u003d\u003d\u003d\u003d\u003d\u003d\u003d\u003d\u003d\u003d\u003d\u003d\u003d\u003d\u003d\u003d\u003d\u003d\u003d\u003d\u003d\u003d\u003d\u003d\u003d\u003d\u003d\u003d\u003d\u003d\u003d\u003d\u003d\u003d\u003d\u003d\u003d\u003d\u003d\u003d\u003d\u003d\u003d\u003d\u003d\u003d\u003d\u003d"
      },
      {
        "lineNumber": 47,
        "author": {
          "gitId": "itskesin"
        },
        "content": "Oops! Please include /at follows by the date (â•¥_â•¥)"
      },
      {
        "lineNumber": 48,
        "author": {
          "gitId": "itskesin"
        },
        "content": "\u003d\u003d\u003d\u003d\u003d\u003d\u003d\u003d\u003d\u003d\u003d\u003d\u003d\u003d\u003d\u003d\u003d\u003d\u003d\u003d\u003d\u003d\u003d\u003d\u003d\u003d\u003d\u003d\u003d\u003d\u003d\u003d\u003d\u003d\u003d\u003d\u003d\u003d\u003d\u003d\u003d\u003d\u003d\u003d\u003d\u003d\u003d\u003d\u003d\u003d\u003d"
      },
      {
        "lineNumber": 49,
        "author": {
          "gitId": "itskesin"
        },
        "content": "                     Got it. I\u0027ve added this task:"
      },
      {
        "lineNumber": 50,
        "author": {
          "gitId": "itskesin"
        },
        "content": "                                   [T][✘] homework"
      },
      {
        "lineNumber": 51,
        "author": {
          "gitId": "itskesin"
        },
        "content": ""
      },
      {
        "lineNumber": 52,
        "author": {
          "gitId": "itskesin"
        },
        "content": "                     4 tasks in the list (â•¥_â•¥)"
      },
      {
        "lineNumber": 53,
        "author": {
          "gitId": "itskesin"
        },
        "content": "\u003d\u003d\u003d\u003d\u003d\u003d\u003d\u003d\u003d\u003d\u003d\u003d\u003d\u003d\u003d\u003d\u003d\u003d\u003d\u003d\u003d\u003d\u003d\u003d\u003d\u003d\u003d\u003d\u003d\u003d\u003d\u003d\u003d\u003d\u003d\u003d\u003d\u003d\u003d\u003d\u003d\u003d\u003d\u003d\u003d\u003d\u003d\u003d\u003d\u003d\u003d"
      },
      {
        "lineNumber": 54,
        "author": {
          "gitId": "itskesin"
        },
        "content": "Task not included in the list, please try again."
      },
      {
        "lineNumber": 55,
        "author": {
          "gitId": "itskesin"
        },
        "content": "\u003d\u003d\u003d\u003d\u003d\u003d\u003d\u003d\u003d\u003d\u003d\u003d\u003d\u003d\u003d\u003d\u003d\u003d\u003d\u003d\u003d\u003d\u003d\u003d\u003d\u003d\u003d\u003d\u003d\u003d\u003d\u003d\u003d\u003d\u003d\u003d\u003d\u003d\u003d\u003d\u003d\u003d\u003d\u003d\u003d\u003d\u003d\u003d\u003d\u003d\u003d"
      },
      {
        "lineNumber": 56,
        "author": {
          "gitId": "itskesin"
        },
        "content": "                     Got it. I\u0027ve added this task:"
      },
      {
        "lineNumber": 57,
        "author": {
          "gitId": "itskesin"
        },
        "content": "                            [T][✘] CS2113T project"
      },
      {
        "lineNumber": 58,
        "author": {
          "gitId": "itskesin"
        },
        "content": ""
      },
      {
        "lineNumber": 59,
        "author": {
          "gitId": "itskesin"
        },
        "content": "                     5 tasks in the list (â•¥_â•¥)"
      },
      {
        "lineNumber": 60,
        "author": {
          "gitId": "itskesin"
        },
        "content": "\u003d\u003d\u003d\u003d\u003d\u003d\u003d\u003d\u003d\u003d\u003d\u003d\u003d\u003d\u003d\u003d\u003d\u003d\u003d\u003d\u003d\u003d\u003d\u003d\u003d\u003d\u003d\u003d\u003d\u003d\u003d\u003d\u003d\u003d\u003d\u003d\u003d\u003d\u003d\u003d\u003d\u003d\u003d\u003d\u003d\u003d\u003d\u003d\u003d\u003d\u003d"
      },
      {
        "lineNumber": 61,
        "author": {
          "gitId": "itskesin"
        },
        "content": "                    Got it. I\u0027ve added this event:"
      },
      {
        "lineNumber": 62,
        "author": {
          "gitId": "itskesin"
        },
        "content": "          [E][✘] project meeting (at:Friday 2-4pm)"
      },
      {
        "lineNumber": 63,
        "author": {
          "gitId": "itskesin"
        },
        "content": ""
      },
      {
        "lineNumber": 64,
        "author": {
          "gitId": "itskesin"
        },
        "content": "                     6 tasks in the list (â•¥_â•¥)"
      },
      {
        "lineNumber": 65,
        "author": {
          "gitId": "itskesin"
        },
        "content": "\u003d\u003d\u003d\u003d\u003d\u003d\u003d\u003d\u003d\u003d\u003d\u003d\u003d\u003d\u003d\u003d\u003d\u003d\u003d\u003d\u003d\u003d\u003d\u003d\u003d\u003d\u003d\u003d\u003d\u003d\u003d\u003d\u003d\u003d\u003d\u003d\u003d\u003d\u003d\u003d\u003d\u003d\u003d\u003d\u003d\u003d\u003d\u003d\u003d\u003d\u003d"
      },
      {
        "lineNumber": 66,
        "author": {
          "gitId": "itskesin"
        },
        "content": "        (â•¥_â•¥) Oops! Information is incomplete."
      },
      {
        "lineNumber": 67,
        "author": {
          "gitId": "itskesin"
        },
        "content": "\u003d\u003d\u003d\u003d\u003d\u003d\u003d\u003d\u003d\u003d\u003d\u003d\u003d\u003d\u003d\u003d\u003d\u003d\u003d\u003d\u003d\u003d\u003d\u003d\u003d\u003d\u003d\u003d\u003d\u003d\u003d\u003d\u003d\u003d\u003d\u003d\u003d\u003d\u003d\u003d\u003d\u003d\u003d\u003d\u003d\u003d\u003d\u003d\u003d\u003d\u003d"
      },
      {
        "lineNumber": 68,
        "author": {
          "gitId": "itskesin"
        },
        "content": "                 Got it. I\u0027ve added this deadline:"
      },
      {
        "lineNumber": 69,
        "author": {
          "gitId": "itskesin"
        },
        "content": "           [D][✘] report submission (by: Thursday)"
      },
      {
        "lineNumber": 70,
        "author": {
          "gitId": "itskesin"
        },
        "content": ""
      },
      {
        "lineNumber": 71,
        "author": {
          "gitId": "itskesin"
        },
        "content": "                     7 tasks in the list (â•¥_â•¥)"
      },
      {
        "lineNumber": 72,
        "author": {
          "gitId": "itskesin"
        },
        "content": "\u003d\u003d\u003d\u003d\u003d\u003d\u003d\u003d\u003d\u003d\u003d\u003d\u003d\u003d\u003d\u003d\u003d\u003d\u003d\u003d\u003d\u003d\u003d\u003d\u003d\u003d\u003d\u003d\u003d\u003d\u003d\u003d\u003d\u003d\u003d\u003d\u003d\u003d\u003d\u003d\u003d\u003d\u003d\u003d\u003d\u003d\u003d\u003d\u003d\u003d\u003d"
      },
      {
        "lineNumber": 73,
        "author": {
          "gitId": "itskesin"
        },
        "content": "                  Here are the tasks in your list:"
      },
      {
        "lineNumber": 74,
        "author": {
          "gitId": "itskesin"
        },
        "content": "                             1. [T][✓] borrow book"
      },
      {
        "lineNumber": 75,
        "author": {
          "gitId": "itskesin"
        },
        "content": "                2. [D][✓] return book (by: Monday)"
      },
      {
        "lineNumber": 76,
        "author": {
          "gitId": "itskesin"
        },
        "content": "                                   3. [T][✘] study"
      },
      {
        "lineNumber": 77,
        "author": {
          "gitId": "itskesin"
        },
        "content": "                                4. [T][✘] homework"
      },
      {
        "lineNumber": 78,
        "author": {
          "gitId": "itskesin"
        },
        "content": "                         5. [T][✘] CS2113T project"
      },
      {
        "lineNumber": 79,
        "author": {
          "gitId": "itskesin"
        },
        "content": "       6. [E][✘] project meeting (at:Friday 2-4pm)"
      },
      {
        "lineNumber": 80,
        "author": {
          "gitId": "itskesin"
        },
        "content": "        7. [D][✘] report submission (by: Thursday)"
      },
      {
        "lineNumber": 81,
        "author": {
          "gitId": "itskesin"
        },
        "content": "\u003d\u003d\u003d\u003d\u003d\u003d\u003d\u003d\u003d\u003d\u003d\u003d\u003d\u003d\u003d\u003d\u003d\u003d\u003d\u003d\u003d\u003d\u003d\u003d\u003d\u003d\u003d\u003d\u003d\u003d\u003d\u003d\u003d\u003d\u003d\u003d\u003d\u003d\u003d\u003d\u003d\u003d\u003d\u003d\u003d\u003d\u003d\u003d\u003d\u003d\u003d"
      },
      {
        "lineNumber": 82,
        "author": {
          "gitId": "itskesin"
        },
        "content": "        Noted. I\u0027ve removed this task: (ï¼¾â–½ï¼¾)"
      },
      {
        "lineNumber": 83,
        "author": {
          "gitId": "itskesin"
        },
        "content": "                                [T][✓] borrow book"
      },
      {
        "lineNumber": 84,
        "author": {
          "gitId": "itskesin"
        },
        "content": "                 Now you have 6 tasks in the list."
      },
      {
        "lineNumber": 85,
        "author": {
          "gitId": "itskesin"
        },
        "content": "\u003d\u003d\u003d\u003d\u003d\u003d\u003d\u003d\u003d\u003d\u003d\u003d\u003d\u003d\u003d\u003d\u003d\u003d\u003d\u003d\u003d\u003d\u003d\u003d\u003d\u003d\u003d\u003d\u003d\u003d\u003d\u003d\u003d\u003d\u003d\u003d\u003d\u003d\u003d\u003d\u003d\u003d\u003d\u003d\u003d\u003d\u003d\u003d\u003d\u003d\u003d"
      },
      {
        "lineNumber": 86,
        "author": {
          "gitId": "itskesin"
        },
        "content": "           Bye, kesin. Hope to see you again soon!"
      },
      {
        "lineNumber": 87,
        "author": {
          "gitId": "itskesin"
        },
        "content": "\u003d\u003d\u003d\u003d\u003d\u003d\u003d\u003d\u003d\u003d\u003d\u003d\u003d\u003d\u003d\u003d\u003d\u003d\u003d\u003d\u003d\u003d\u003d\u003d\u003d\u003d\u003d\u003d\u003d\u003d\u003d\u003d\u003d\u003d\u003d\u003d\u003d\u003d\u003d\u003d\u003d\u003d\u003d\u003d\u003d\u003d\u003d\u003d\u003d\u003d\u003d"
      }
    ],
    "authorContributionMap": {
      "itskesin": 87
    }
  },
  {
    "path": "test-ui-test/input.txt",
    "fileType": "txt",
    "lines": [
      {
        "lineNumber": 1,
        "author": {
          "gitId": "itskesin"
        },
        "content": "kesin"
      },
      {
        "lineNumber": 2,
        "author": {
          "gitId": "itskesin"
        },
        "content": "todo borrow book"
      },
      {
        "lineNumber": 3,
        "author": {
          "gitId": "itskesin"
        },
        "content": "event"
      },
      {
        "lineNumber": 4,
        "author": {
          "gitId": "itskesin"
        },
        "content": "delete 3"
      },
      {
        "lineNumber": 5,
        "author": {
          "gitId": "itskesin"
        },
        "content": "deadline return book /by Monday"
      },
      {
        "lineNumber": 6,
        "author": {
          "gitId": "itskesin"
        },
        "content": "todo study"
      },
      {
        "lineNumber": 7,
        "author": {
          "gitId": "itskesin"
        },
        "content": "done 1"
      },
      {
        "lineNumber": 8,
        "author": {
          "gitId": "itskesin"
        },
        "content": "deadline report"
      },
      {
        "lineNumber": 9,
        "author": {
          "gitId": "itskesin"
        },
        "content": "done 2"
      },
      {
        "lineNumber": 10,
        "author": {
          "gitId": "itskesin"
        },
        "content": "list"
      },
      {
        "lineNumber": 11,
        "author": {
          "gitId": "itskesin"
        },
        "content": "event party"
      },
      {
        "lineNumber": 12,
        "author": {
          "gitId": "itskesin"
        },
        "content": "todo homework"
      },
      {
        "lineNumber": 13,
        "author": {
          "gitId": "itskesin"
        },
        "content": "done 5"
      },
      {
        "lineNumber": 14,
        "author": {
          "gitId": "itskesin"
        },
        "content": "todo CS2113T project"
      },
      {
        "lineNumber": 15,
        "author": {
          "gitId": "itskesin"
        },
        "content": "event project meeting /at Friday 2-4pm"
      },
      {
        "lineNumber": 16,
        "author": {
          "gitId": "itskesin"
        },
        "content": "todo"
      },
      {
        "lineNumber": 17,
        "author": {
          "gitId": "itskesin"
        },
        "content": "deadline report submission /by Thursday"
      },
      {
        "lineNumber": 18,
        "author": {
          "gitId": "itskesin"
        },
        "content": "list"
      },
      {
        "lineNumber": 19,
        "author": {
          "gitId": "itskesin"
        },
        "content": "delete 1"
      },
      {
        "lineNumber": 20,
        "author": {
          "gitId": "itskesin"
        },
        "content": "bye"
      }
    ],
    "authorContributionMap": {
      "itskesin": 20
    }
  },
  {
    "path": "test-ui-test/runtest.bat",
    "fileType": "bat",
    "lines": [
      {
        "lineNumber": 1,
        "author": {
          "gitId": "itskesin"
        },
        "content": "@ECHO OFF"
      },
      {
        "lineNumber": 2,
        "author": {
          "gitId": "itskesin"
        },
        "content": ""
      },
      {
        "lineNumber": 3,
        "author": {
          "gitId": "itskesin"
        },
        "content": "REM create bin directory if it doesn\u0027t exist"
      },
      {
        "lineNumber": 4,
        "author": {
          "gitId": "itskesin"
        },
        "content": "if not exist ..\\bin mkdir ..\\bin"
      },
      {
        "lineNumber": 5,
        "author": {
          "gitId": "itskesin"
        },
        "content": ""
      },
      {
        "lineNumber": 6,
        "author": {
          "gitId": "itskesin"
        },
        "content": "REM delete output from previous run"
      },
      {
        "lineNumber": 7,
        "author": {
          "gitId": "itskesin"
        },
        "content": "del ACTUAL.TXT"
      },
      {
        "lineNumber": 8,
        "author": {
          "gitId": "itskesin"
        },
        "content": ""
      },
      {
        "lineNumber": 9,
        "author": {
          "gitId": "itskesin"
        },
        "content": "REM compile the code into the bin folder"
      },
      {
        "lineNumber": 10,
        "author": {
          "gitId": "itskesin"
        },
        "content": "javac  -cp ..\\src -Xlint:none -d ..\\bin ..\\src\\main\\java\\duke\\*.java ..\\src\\main\\java\\duke\\task\\*.java"
      },
      {
        "lineNumber": 11,
        "author": {
          "gitId": "itskesin"
        },
        "content": "IF ERRORLEVEL 1 ("
      },
      {
        "lineNumber": 12,
        "author": {
          "gitId": "itskesin"
        },
        "content": "    echo ********** BUILD FAILURE **********"
      },
      {
        "lineNumber": 13,
        "author": {
          "gitId": "itskesin"
        },
        "content": "    exit /b 1"
      },
      {
        "lineNumber": 14,
        "author": {
          "gitId": "itskesin"
        },
        "content": ")"
      },
      {
        "lineNumber": 15,
        "author": {
          "gitId": "itskesin"
        },
        "content": "REM no error here, errorlevel \u003d\u003d 0"
      },
      {
        "lineNumber": 16,
        "author": {
          "gitId": "itskesin"
        },
        "content": ""
      },
      {
        "lineNumber": 17,
        "author": {
          "gitId": "itskesin"
        },
        "content": "REM run the program, feed commands from input.txt file and redirect the output to the ACTUAL.TXT"
      },
      {
        "lineNumber": 18,
        "author": {
          "gitId": "itskesin"
        },
        "content": "java -Dfile.encoding\u003dUTF8 -classpath ..\\bin duke.Duke \u003c input.txt \u003e ACTUAL.TXT"
      },
      {
        "lineNumber": 19,
        "author": {
          "gitId": "itskesin"
        },
        "content": ""
      },
      {
        "lineNumber": 20,
        "author": {
          "gitId": "itskesin"
        },
        "content": "REM compare the output to the expected output"
      },
      {
        "lineNumber": 21,
        "author": {
          "gitId": "itskesin"
        },
        "content": "FC ACTUAL.TXT EXPECTED.TXT"
      }
    ],
    "authorContributionMap": {
      "itskesin": 21
    }
  }
]
